fossa/__init__.py
fossa/_version.py
fossa/base.py
fossa/simple.py
fossa/utils.py
fossa-0.0.3.dist-info/DESCRIPTION.rst
fossa-0.0.3.dist-info/METADATA
fossa-0.0.3.dist-info/RECORD
fossa-0.0.3.dist-info/WHEEL
fossa-0.0.3.dist-info/metadata.json
fossa-0.0.3.dist-info/top_level.txt
tests/__init__.py
tests/test_common.py
tests/test_latest_window.py
