Metadata-Version: 2.0
Name: fossa
Version: 0.0.3
Summary: Distribution-based anomaly detection for time series.
Home-page: https://github.com/shaypal5/fossa
Author: Shay Palachy
Author-email: shay.palachy@gmail.com
License: MIT
Platform: UNKNOWN
Classifier: Development Status :: 4 - Beta
Classifier: License :: OSI Approved :: MIT License
Classifier: Programming Language :: Python
Classifier: Programming Language :: Python :: 3.5
Classifier: Programming Language :: Python :: 3.6
Classifier: Topic :: Software Development :: Libraries
Classifier: Topic :: Software Development :: Libraries :: Python Modules
Classifier: Intended Audience :: Developers
Requires-Python: >=3.5
Requires-Dist: numpy
Requires-Dist: scipy
Requires-Dist: scikit-learn
Requires-Dist: pandas
Provides-Extra: test
Requires-Dist: pytest; extra == 'test'
Requires-Dist: coverage; extra == 'test'
Requires-Dist: pytest-cov; extra == 'test'
Requires-Dist: collective.checkdocs; extra == 'test'
Requires-Dist: pygments; extra == 'test'
Requires-Dist: numpy; extra == 'test'
Requires-Dist: scipy; extra == 'test'
Requires-Dist: scikit-learn; extra == 'test'
Requires-Dist: pandas; extra == 'test'
